hydra_logger/__init__.py
hydra_logger/compatibility.py
hydra_logger/config.py
hydra_logger/logger.py
hydra_logger-0.2.0.dist-info/licenses/LICENSE
hydra_logger-0.2.0.dist-info/METADATA
hydra_logger-0.2.0.dist-info/WHEEL
hydra_logger-0.2.0.dist-info/entry_points.txt
hydra_logger-0.2.0.dist-info/top_level.txt
hydra_logger-0.2.0.dist-info/RECORD
