Metadata-Version: 2.4
Name: hydra-logger
Version: 0.2.0
Summary: A multi-layered, configurable logging system with custom folder paths and event integration
Home-page: https://github.com/SavinRazvan/hydra-logger
Author: Savin Ionut Razvan
Author-email: Savin Ionut Razvan <razvan.i.savin@gmail.com>
License: MIT
Project-URL: Homepage, https://github.com/SavinRazvan/hydra-logger
Project-URL: Repository, https://github.com/SavinRazvan/hydra-logger
Project-URL: Documentation, https://github.com/SavinRazvan/hydra-logger#readme
Project-URL: Bug Tracker, https://github.com/SavinRazvan/hydra-logger/issues
Classifier: Development Status :: 3 - Alpha
Classifier: Intended Audience :: Developers
Classifier: Programming Language :: Python :: 3.8
Classifier: Programming Language :: Python :: 3.9
Classifier: Programming Language :: Python :: 3.11
Classifier: Programming Language :: Python :: 3.12
Classifier: Programming Language :: Python :: 3.13
Classifier: Topic :: System :: Logging
Classifier: Topic :: Software Development :: Libraries :: Python Modules
Requires-Python: >=3.8
License-File: LICENSE
Requires-Dist: pydantic>=2.0.0
Requires-Dist: pyyaml>=6.0
Requires-Dist: tomli>=2.0.0; python_version < "3.11"
Provides-Extra: dev
Requires-Dist: pytest>=7.0.0; extra == "dev"
Requires-Dist: pytest-cov>=4.0.0; extra == "dev"
Requires-Dist: pytest-mock>=3.10.0; extra == "dev"
Requires-Dist: black>=23.0.0; extra == "dev"
Requires-Dist: flake8>=6.0.0; extra == "dev"
Requires-Dist: isort>=5.12.0; extra == "dev"
Requires-Dist: mypy>=1.0.0; extra == "dev"
Requires-Dist: bandit>=1.7.0; extra == "dev"
Requires-Dist: safety>=2.3.0; extra == "dev"
Requires-Dist: types-PyYAML>=6.0.0; extra == "dev"
Provides-Extra: json
Requires-Dist: python-json-logger>=2.0.0; extra == "json"
Provides-Extra: gelf
Requires-Dist: graypy>=2.1.0; extra == "gelf"
Provides-Extra: all
Requires-Dist: python-json-logger>=2.0.0; extra == "all"
Requires-Dist: graypy>=2.1.0; extra == "all"
Dynamic: author
Dynamic: home-page
Dynamic: license-file
Dynamic: requires-python
